pgnote/__init__.py
pgnote/event/__init__.py
pgnote/event/exam_event.py
pgnote/log/__init__.py
pgnote/obj/__init__.py
pgnote/obj/types.py
pgnote/page/__init__.py
pgnote-0.0.4.dist-info/LICENSE
pgnote-0.0.4.dist-info/METADATA
pgnote-0.0.4.dist-info/WHEEL
pgnote-0.0.4.dist-info/top_level.txt
pgnote-0.0.4.dist-info/RECORD
